{
    "displayName": "Circulation: Inhouse Counts by Location",
    "description": "Inhouse counts by shelving location",
    "instructions": "Enter parameters.",
    "parameters": [
        {
            "name": "start_date",
            "displayName": "Start date (mm-dd-yyyy)",
            "type": "date",
            "required": false
        },
        {
            "name": "end_date",
            "displayName": "End date (mm-dd-yyyy)",
            "type": "date",
            "required": false
        },
        {
            "name": "campus_prefix",
            "displayName": "Enter campus prefix (MST, MU, UMKC, UMSL)",
            "type": "text",
            "required": false
        }
    ]
}
